shuttlis/__init__.py
shuttlis/generics.py
shuttlis/instrumentation.py
shuttlis/money.py
shuttlis/pagination.py
shuttlis/serialization.py
shuttlis/set.py
shuttlis/utils.py
shuttlis/validators.py
shuttlis/log/__init__.py
shuttlis/log/filters.py
shuttlis/log/formatters.py
shuttlis/log/log.py
shuttlis/log/utils.py
shuttlis/time/__init__.py
shuttlis/time/military_time.py
shuttlis/time/time.py
shuttlis/time/weekday.py
tests/__init__.py
tests/test_generics.py
tests/test_log.py
tests/test_money.py
tests/test_pagination.py
tests/test_serialization.py
tests/test_set.py
tests/test_utils.py
tests/test_validators.py
shuttlis-0.1.53.dist-info/METADATA
shuttlis-0.1.53.dist-info/WHEEL
shuttlis-0.1.53.dist-info/top_level.txt
shuttlis-0.1.53.dist-info/RECORD
