Metadata-Version: 2.1
Name: shuttlis
Version: 0.1.53
Summary: Utilities
Home-page: https://github.com/shuttl-tech/pyshuttlis
Author: Shuttl
Author-email: sherub.thakur@shuttl.com
License: MIT
Platform: UNKNOWN
Classifier: Programming Language :: Python :: 3.7
Requires-Dist: pytz
Requires-Dist: voluptuous
Requires-Dist: ddtrace (==0.36.1)
Requires-Dist: sentry-sdk (>=0.16.1)
Provides-Extra: dev
Requires-Dist: flake8 ; extra == 'dev'
Provides-Extra: test
Requires-Dist: pytest ; extra == 'test'
Requires-Dist: pytest-runner ; extra == 'test'
Requires-Dist: pytest-cov ; extra == 'test'
Requires-Dist: pytest-pep8 ; extra == 'test'
